README.rst
setup.py
blirupchat/client.py
blirupchat/server.py
blirupchat.egg-info/PKG-INFO
blirupchat.egg-info/SOURCES.txt
blirupchat.egg-info/dependency_links.txt
blirupchat.egg-info/not-zip-safe
blirupchat.egg-info/top_level.txt