Metadata-Version: 1.0
Name: blirupchat
Version: 1.0.0
Summary: Chat Client and Server
Home-page: https://github.com/Blirup/chat.git
Author: Blirup
Author-email: martin.blirup@gmail.com
License: GPL-3.0
Platform: UNKNOWN
